bootstrap.py
buildout.cfg
setup.py
src/zc/__init__.py
src/zc.creditcard.egg-info/PKG-INFO
src/zc.creditcard.egg-info/SOURCES.txt
src/zc.creditcard.egg-info/dependency_links.txt
src/zc.creditcard.egg-info/namespace_packages.txt
src/zc.creditcard.egg-info/requires.txt
src/zc.creditcard.egg-info/top_level.txt
src/zc/creditcard/__init__.py
src/zc/creditcard/tests.py
