Metadata-Version: 1.0
Name: zc.creditcard
Version: 1.0
Summary: Utilities for credit card processing
Home-page: UNKNOWN
Author: Zope Corporation
Author-email: zope3-dev#zope.org
License: ZPL 2.1
Keywords: cc credit card
Platform: UNKNOWN
